djadmin_detail_view/__init__.py
djadmin_detail_view/apps.py
djadmin_detail_view/defaults.py
djadmin_detail_view/mixins.py
djadmin_detail_view/static/djadmin_detail_view/js/controllers/lazy_panel_controller.js
djadmin_detail_view/template_helpers.py
djadmin_detail_view/templates/admin/djadmin_components/_auto_col.html
djadmin_detail_view/templates/admin/djadmin_components/_auto_header.html
djadmin_detail_view/templates/admin/djadmin_components/_auto_row_col.html
djadmin_detail_view/templates/admin/djadmin_components/auto_layout_detail.html
djadmin_detail_view/templates/admin/djadmin_components/lazy_placeholder.html
djadmin_detail_view/templates/admin/djadmin_components/object_details.html
djadmin_detail_view/templates/admin/djadmin_components/object_list.html
djadmin_detail_view/templates/admin/djadmin_components/preview_file.html
djadmin_detail_view/templatetags/djadmin_tags.py
djadmin_detail_view/url_helpers.py
djadmin_detail_view-0.4.4.dist-info/METADATA
djadmin_detail_view-0.4.4.dist-info/WHEEL
djadmin_detail_view-0.4.4.dist-info/licenses/LICENSE
djadmin_detail_view-0.4.4.dist-info/RECORD
