Metadata-Version: 2.4
Name: djadmin-detail-view
Version: 0.4.4
Summary: 
License-File: LICENSE
Author: Justin Louie
Author-email: 224840+nitsujri@users.noreply.github.com
Requires-Python: >=3.11,<4.0
Classifier: Programming Language :: Python :: 3
Classifier: Programming Language :: Python :: 3.11
Classifier: Programming Language :: Python :: 3.12
Classifier: Programming Language :: Python :: 3.13
Classifier: Programming Language :: Python :: 3.14
Requires-Dist: django (>=4.0)
Requires-Dist: django-environ (>=0.11.2,<0.12.0)
Requires-Dist: django-webpack-loader (>=3.0.1,<4.0.0)
Requires-Dist: pytest-django (>=4.7.0,<5.0.0)
Requires-Dist: requests (>=2.31.0,<3.0.0)
Requires-Dist: whitenoise (>=6.6.0,<7.0.0)
